chat_trainer_akki/__init__.py
chat_trainer_akki-0.3.dist-info/METADATA
chat_trainer_akki-0.3.dist-info/WHEEL
chat_trainer_akki-0.3.dist-info/top_level.txt
chat_trainer_akki-0.3.dist-info/RECORD
