Metadata-Version: 2.1
Name: chat-trainer-akki
Version: 0.3
Summary: code trainer package
Author: Akshat
Requires-Dist: nltk
Requires-Dist: tensorflow
Requires-Dist: numpy
